pypmxvmd/__init__.py
pypmxvmd/common/__init__.py
pypmxvmd/common/io/__init__.py
pypmxvmd/common/io/_fast_binary.c
pypmxvmd/common/io/_fast_binary.cp310-win_amd64.pyd
pypmxvmd/common/io/_fast_binary.cp311-win_amd64.pyd
pypmxvmd/common/io/_fast_binary.cp38-win_amd64.pyd
pypmxvmd/common/io/_fast_binary.pyi
pypmxvmd/common/io/_fast_binary.pyx
pypmxvmd/common/io/binary_io.py
pypmxvmd/common/io/file_utils.py
pypmxvmd/common/io/text_io.py
pypmxvmd/common/models/__init__.py
pypmxvmd/common/models/base.py
pypmxvmd/common/models/pmx.py
pypmxvmd/common/models/vmd.py
pypmxvmd/common/models/vpd.py
pypmxvmd/common/parsers/__init__.py
pypmxvmd/common/parsers/_fast_pmx.c
pypmxvmd/common/parsers/_fast_pmx.cp310-win_amd64.pyd
pypmxvmd/common/parsers/_fast_pmx.cp311-win_amd64.pyd
pypmxvmd/common/parsers/_fast_pmx.cp38-win_amd64.pyd
pypmxvmd/common/parsers/_fast_pmx.pyi
pypmxvmd/common/parsers/_fast_pmx.pyx
pypmxvmd/common/parsers/_fast_vmd.c
pypmxvmd/common/parsers/_fast_vmd.cp310-win_amd64.pyd
pypmxvmd/common/parsers/_fast_vmd.cp311-win_amd64.pyd
pypmxvmd/common/parsers/_fast_vmd.cp38-win_amd64.pyd
pypmxvmd/common/parsers/_fast_vmd.pyi
pypmxvmd/common/parsers/_fast_vmd.pyx
pypmxvmd/common/parsers/pmx_parser.py
pypmxvmd/common/parsers/pmx_parser_nuthouse.py
pypmxvmd/common/parsers/vmd_parser.py
pypmxvmd/common/parsers/vmd_parser_nuthouse.py
pypmxvmd/common/parsers/vpd_parser.py
pypmxvmd-2.7.2.dist-info/METADATA
pypmxvmd-2.7.2.dist-info/WHEEL
pypmxvmd-2.7.2.dist-info/entry_points.txt
pypmxvmd-2.7.2.dist-info/top_level.txt
pypmxvmd-2.7.2.dist-info/RECORD
