Metadata-Version: 2.4
Name: pypmxvmd
Version: 2.7.2
Summary: Python MikuMikuDance file parser library for VMD, PMX, and VPD.
Author-email: PythonImporter <271374667@qq.com>
Project-URL: Homepage, https://github.com/271374667/pypmxvmd
Project-URL: Documentation, https://271374667.github.io/pypmxvmd/
Project-URL: Repository, https://github.com/271374667/pypmxvmd
Project-URL: Bug Tracker, https://github.com/271374667/pypmxvmd/issues
Keywords: mmd,mikumikudance,pmx,vmd,vpd,3d,animation
Classifier: Development Status :: 4 - Beta
Classifier: Intended Audience :: Developers
Classifier: License :: OSI Approved :: MIT License
Classifier: Programming Language :: Python :: 3
Classifier: Programming Language :: Python :: 3.8
Classifier: Programming Language :: Python :: 3.9
Classifier: Programming Language :: Python :: 3.10
Classifier: Programming Language :: Python :: 3.11
Classifier: Topic :: Multimedia :: Graphics :: 3D Modeling
Classifier: Topic :: Software Development :: Libraries :: Python Modules
Requires-Python: >=3.8
Requires-Dist: typing-extensions>=4.0.0; python_version < "3.10"
